MANIFEST.in
README.txt
setup.py
collective/__init__.py
collective.kuputabs.egg-info/PKG-INFO
collective.kuputabs.egg-info/SOURCES.txt
collective.kuputabs.egg-info/dependency_links.txt
collective.kuputabs.egg-info/entry_points.txt
collective.kuputabs.egg-info/namespace_packages.txt
collective.kuputabs.egg-info/not-zip-safe
collective.kuputabs.egg-info/paster_plugins.txt
collective.kuputabs.egg-info/requires.txt
collective.kuputabs.egg-info/top_level.txt
collective/kuputabs/__init__.py
collective/kuputabs/configure.zcml
collective/kuputabs/profiles.zcml
collective/kuputabs/setuphandlers.py
collective/kuputabs/skins.zcml
collective/kuputabs/tests.py
collective/kuputabs/browser/__init__.py
collective/kuputabs/browser/views.py
collective/kuputabs/profiles/default/cssregistry.xml
collective/kuputabs/profiles/default/import_steps.xml
collective/kuputabs/profiles/default/jsregistry.xml
collective/kuputabs/profiles/default/metadata.xml
collective/kuputabs/profiles/default/skins.xml
collective/kuputabs/skins/kuputabs/kuputabs-alternative.css
collective/kuputabs/skins/kuputabs/kuputabs.css.dtml
collective/kuputabs/skins/kuputabs/kuputabs.css.dtml.metadata
collective/kuputabs/skins/kuputabs/kuputabs.js