Metadata-Version: 1.0
Name: collective.kuputabs
Version: 0.1
Summary: plone.org front page like tabs user editable
Home-page: http://svn.plone.org/svn/plone/plone.app.example
Author: Twinapex Research
Author-email: mikko.ohtamaa@twinapex.com
License: GPL
Keywords: kupu plone zope tabs
Platform: UNKNOWN
Classifier: Framework :: Plone
Classifier: Programming Language :: Python
Classifier: Topic :: Software Development :: Libraries :: Python Modules
